getvoice/__init__.py
getvoice/voice.py
getvoice-0.0.5.dist-info/METADATA
getvoice-0.0.5.dist-info/WHEEL
getvoice-0.0.5.dist-info/top_level.txt
getvoice-0.0.5.dist-info/RECORD
